dockers/__init__.py
dockers/containers/__init__.py
dockers/containers/ticket1.py
dockers/containers/ticket2.py
dockers/containers/ticket3.py
dockers/docker_setup/__init__.py
dockers/docker_setup/ticket1.py
dockers/images/__init__.py
dockers/images/ticket2.py
dockers/images/ticket3.py
dockers/shared_scripts/__init__.py
dockers/shared_scripts/modules.py
dockers/volumes/__init__.py
dockers/volumes/ticket1.py
dockers/volumes/ticket2.py
docker_farrukh90-0.0.50.dist-info/LICENSE
docker_farrukh90-0.0.50.dist-info/METADATA
docker_farrukh90-0.0.50.dist-info/WHEEL
docker_farrukh90-0.0.50.dist-info/top_level.txt
docker_farrukh90-0.0.50.dist-info/RECORD
